{
  "app_name": "GIMP",
  "process_name": "gimp.exe",
  "category": "Graphic Design",
  "platforms": ["windows"],
  "icon_slug": "gimp",
  "brand_color": "#8C8073",
  "shortcuts": [
    {
      "section": "Help",
      "action": "Help",
      "keys": [["F1"]],
      "os": "windows",
      "source": "official",
      "confidence": "high",
      "verified_against_official": true
    },
    {
      "section": "Help",
      "action": "Context help",
      "keys": [["Shift", "F1"]],
      "os": "windows",
      "source": "official",
      "confidence": "high",
      "verified_against_official": true
    },
    {
      "section": "Toolbox",
      "action": "Rectangle select",
      "keys": [["R"]],
      "os": "windows",
      "source": "official",
      "confidence": "high",
      "verified_against_official": true
    },
    {
      "section": "Toolbox",
      "action": "Ellipse select",
      "keys": [["E"]],
      "os": "windows",
      "source": "official",
      "confidence": "high",
      "verified_against_official": true
    },
    {
      "section": "Toolbox",
      "action": "Free select",
      "keys": [["F"]],
      "os": "windows",
      "source": "official",
      "confidence": "high",
      "verified_against_official": true
    },
    {
      "section": "Toolbox",
      "action": "Fuzzy select",
      "keys": [["U"]],
      "os": "windows",
      "source": "official",
      "confidence": "high",
      "verified_against_official": true
    },
    {
      "section": "Toolbox",
      "action": "Select by color",
      "keys": [["Shift", "O"]],
      "os": "windows",
      "source": "official",
      "confidence": "high",
      "verified_against_official": true
    },
    {
      "section": "Toolbox",
      "action": "Scissors",
      "keys": [["I"]],
      "os": "windows",
      "source": "official",
      "confidence": "high",
      "verified_against_official": true
    },
    {
      "section": "Toolbox",
      "action": "Paths",
      "keys": [["B"]],
      "os": "windows",
      "source": "official",
      "confidence": "high",
      "verified_against_official": true
    },
    {
      "section": "Toolbox",
      "action": "Color picker",
      "keys": [["O"]],
      "os": "windows",
      "source": "official",
      "confidence": "high",
      "verified_against_official": true
    },
    {
      "section": "Toolbox",
      "action": "Move",
      "keys": [["M"]],
      "os": "windows",
      "source": "official",
      "confidence": "high",
      "verified_against_official": true
    },
    {
      "section": "Toolbox",
      "action": "Crop and resize",
      "keys": [["Shift", "C"]],
      "os": "windows",
      "source": "official",
      "confidence": "high",
      "verified_against_official": true
    },
    {
      "section": "Toolbox",
      "action": "Rotate",
      "keys": [["Shift", "R"]],
      "os": "windows",
      "source": "official",
      "confidence": "high",
      "verified_against_official": true
    },
    {
      "section": "Toolbox",
      "action": "Scale",
      "keys": [["Shift", "T"]],
      "os": "windows",
      "source": "official",
      "confidence": "high",
      "verified_against_official": true
    },
    {
      "section": "Toolbox",
      "action": "Shear",
      "keys": [["Shift", "S"]],
      "os": "windows",
      "source": "official",
      "confidence": "high",
      "verified_against_official": true
    },
    {
      "section": "Toolbox",
      "action": "Perspective",
      "keys": [["Shift", "P"]],
      "os": "windows",
      "source": "official",
      "confidence": "high",
      "verified_against_official": true
    },
    {
      "section": "Toolbox",
      "action": "Flip",
      "keys": [["Shift", "F"]],
      "os": "windows",
      "source": "official",
      "confidence": "high",
      "verified_against_official": true
    },
    {
      "section": "Toolbox",
      "action": "Text",
      "keys": [["T"]],
      "os": "windows",
      "source": "official",
      "confidence": "high",
      "verified_against_official": true
    },
    {
      "section": "Toolbox",
      "action": "Bucket fill",
      "keys": [["Shift", "B"]],
      "os": "windows",
      "source": "official",
      "confidence": "high",
      "verified_against_official": true
    },
    {
      "section": "Toolbox",
      "action": "Blend",
      "keys": [["L"]],
      "os": "windows",
      "source": "official",
      "confidence": "high",
      "verified_against_official": true
    },
    {
      "section": "Toolbox",
      "action": "Pencil",
      "keys": [["N"]],
      "os": "windows",
      "source": "official",
      "confidence": "high",
      "verified_against_official": true
    },
    {
      "section": "Toolbox",
      "action": "Paintbrush",
      "keys": [["P"]],
      "os": "windows",
      "source": "official",
      "confidence": "high",
      "verified_against_official": true
    },
    {
      "section": "Toolbox",
      "action": "Eraser",
      "keys": [["Shift", "E"]],
      "os": "windows",
      "source": "official",
      "confidence": "high",
      "verified_against_official": true
    },
    {
      "section": "Toolbox",
      "action": "Airbrush",
      "keys": [["A"]],
      "os": "windows",
      "source": "official",
      "confidence": "high",
      "verified_against_official": true
    },
    {
      "section": "Toolbox",
      "action": "Ink",
      "keys": [["K"]],
      "os": "windows",
      "source": "official",
      "confidence": "high",
      "verified_against_official": true
    },
    {
      "section": "Toolbox",
      "action": "Clone",
      "keys": [["C"]],
      "os": "windows",
      "source": "official",
      "confidence": "high",
      "verified_against_official": true
    },
    {
      "section": "Toolbox",
      "action": "Convolve",
      "keys": [["V"]],
      "os": "windows",
      "source": "official",
      "confidence": "high",
      "verified_against_official": true
    },
    {
      "section": "Toolbox",
      "action": "Smudge",
      "keys": [["S"]],
      "os": "windows",
      "source": "official",
      "confidence": "high",
      "verified_against_official": true
    },
    {
      "section": "Toolbox",
      "action": "Dodge or burn",
      "keys": [["Shift", "D"]],
      "os": "windows",
      "source": "official",
      "confidence": "high",
      "verified_against_official": true
    },
    {
      "section": "Toolbox",
      "action": "Swap colors",
      "keys": [["X"]],
      "os": "windows",
      "source": "official",
      "confidence": "high",
      "verified_against_official": true
    },
    {
      "section": "Toolbox",
      "action": "Default colors",
      "keys": [["D"]],
      "os": "windows",
      "source": "official",
      "confidence": "high",
      "verified_against_official": true
    },
    {
      "section": "File",
      "action": "New image",
      "keys": [["Ctrl", "N"]],
      "os": "windows",
      "source": "official",
      "confidence": "high",
      "verified_against_official": true
    },
    {
      "section": "File",
      "action": "Open image",
      "keys": [["Ctrl", "O"]],
      "os": "windows",
      "source": "official",
      "confidence": "high",
      "verified_against_official": true
    },
    {
      "section": "File",
      "action": "Open image as new layer",
      "keys": [["Ctrl", "Alt", "N"]],
      "os": "windows",
      "source": "official",
      "confidence": "high",
      "verified_against_official": true
    },
    {
      "section": "File",
      "action": "Duplicate image",
      "keys": [["Ctrl", "D"]],
      "os": "windows",
      "source": "official",
      "confidence": "high",
      "verified_against_official": true
    },
    {
      "section": "File",
      "action": "Open recent image 1-10",
      "keys": [["Ctrl", "1-0"]],
      "os": "windows",
      "source": "official",
      "confidence": "high",
      "verified_against_official": true
    },
    {
      "section": "File",
      "action": "Save image",
      "keys": [["Ctrl", "S"]],
      "os": "windows",
      "source": "official",
      "confidence": "high",
      "verified_against_official": true
    },
    {
      "section": "File",
      "action": "Save image under a new name",
      "keys": [["Ctrl", "S"]],
      "os": "windows",
      "source": "official",
      "confidence": "high",
      "verified_against_official": true
    },
    {
      "section": "File",
      "action": "Quit",
      "keys": [["Ctrl", "Q"]],
      "os": "windows",
      "source": "official",
      "confidence": "high",
      "verified_against_official": true
    },
    {
      "section": "Dialogs",
      "action": "Layers",
      "keys": [["Ctrl", "L"]],
      "os": "windows",
      "source": "official",
      "confidence": "high",
      "verified_against_official": true
    },
    {
      "section": "Dialogs",
      "action": "Brushes",
      "keys": [["Ctrl", "Shift", "B"]],
      "os": "windows",
      "source": "official",
      "confidence": "high",
      "verified_against_official": true
    },
    {
      "section": "Dialogs",
      "action": "Patterns",
      "keys": [["Ctrl", "Shift", "P"]],
      "os": "windows",
      "source": "official",
      "confidence": "high",
      "verified_against_official": true
    },
    {
      "section": "Dialogs",
      "action": "Gradients",
      "keys": [["Ctrl", "G"]],
      "os": "windows",
      "source": "official",
      "confidence": "high",
      "verified_against_official": true
    },
    {
      "section": "Dialogs",
      "action": "Tool options",
      "keys": [["Ctrl", "Shift", "T"]],
      "os": "windows",
      "source": "official",
      "confidence": "high",
      "verified_against_official": true
    },
    {
      "section": "Dialogs",
      "action": "Palettes",
      "keys": [["Ctrl", "P"]],
      "os": "windows",
      "source": "official",
      "confidence": "high",
      "verified_against_official": true
    },
    {
      "section": "Dialogs",
      "action": "Info window",
      "keys": [["Ctrl", "Shift", "I"]],
      "os": "windows",
      "source": "official",
      "confidence": "high",
      "verified_against_official": true
    },
    {
      "section": "Dialogs",
      "action": "Navigation window",
      "keys": [["Ctrl", "Shift", "N"]],
      "os": "windows",
      "source": "official",
      "confidence": "high",
      "verified_against_official": true
    },
    {
      "section": "Dialogs",
      "action": "Jump to next widget",
      "keys": [["Tab"]],
      "os": "windows",
      "source": "official",
      "confidence": "high",
      "verified_against_official": true
    },
    {
      "section": "Dialogs",
      "action": "Jump to previous widget",
      "keys": [["Shift", "Tab"]],
      "os": "windows",
      "source": "official",
      "confidence": "high",
      "verified_against_official": true
    },
    {
      "section": "Dialogs",
      "action": "Set the new value",
      "keys": [["Enter"]],
      "os": "windows",
      "source": "official",
      "confidence": "high",
      "verified_against_official": true
    },
    {
      "section": "Dialogs",
      "action": "Activate the current button or list",
      "keys": [["Space"]],
      "os": "windows",
      "source": "official",
      "confidence": "high",
      "verified_against_official": true
    },
    {
      "section": "Dialogs",
      "action": "In a multi-tab dialog, switch tabs",
      "keys": [["Ctrl", "Alt", "PgUp"]],
      "os": "windows",
      "source": "official",
      "confidence": "high",
      "verified_against_official": true
    },
    {
      "section": "Dialogs",
      "action": "Open location",
      "keys": [["Shift", "L"]],
      "os": "windows",
      "source": "official",
      "confidence": "high",
      "verified_against_official": true
    },
    {
      "section": "Dialogs",
      "action": "Up folder",
      "keys": [["Alt", "Up"]],
      "os": "windows",
      "source": "official",
      "confidence": "high",
      "verified_against_official": true
    },
    {
      "section": "Dialogs",
      "action": "Down folder",
      "keys": [["Alt", "Down"]],
      "os": "windows",
      "source": "official",
      "confidence": "high",
      "verified_against_official": true
    },
    {
      "section": "Dialogs",
      "action": "Home folder",
      "keys": [["Alt", "Home"]],
      "os": "windows",
      "source": "official",
      "confidence": "high",
      "verified_against_official": true
    },
    {
      "section": "Dialogs",
      "action": "Close dialog",
      "keys": [["Esc"]],
      "os": "windows",
      "source": "official",
      "confidence": "high",
      "verified_against_official": true
    },
    {
      "section": "View",
      "action": "Main menu",
      "keys": [["F10"]],
      "os": "windows",
      "source": "official",
      "confidence": "high",
      "verified_against_official": true
    },
    {
      "section": "View",
      "action": "Drop-down menu",
      "keys": [["Shift", "F10"]],
      "os": "windows",
      "source": "official",
      "confidence": "high",
      "verified_against_official": true
    },
    {
      "section": "View",
      "action": "Toggle fullscreen",
      "keys": [["F11"]],
      "os": "windows",
      "source": "official",
      "confidence": "high",
      "verified_against_official": true
    },
    {
      "section": "View",
      "action": "Toggle quickmask",
      "keys": [["Shift", "Q"]],
      "os": "windows",
      "source": "official",
      "confidence": "high",
      "verified_against_official": true
    },
    {
      "section": "View",
      "action": "Close document window",
      "keys": [["Ctrl", "W"]],
      "os": "windows",
      "source": "official",
      "confidence": "high",
      "verified_against_official": true
    },
    {
      "section": "View",
      "action": "Zoom in",
      "keys": [["+"]],
      "os": "windows",
      "source": "official",
      "confidence": "high",
      "verified_against_official": true
    },
    {
      "section": "View",
      "action": "Zoom out",
      "keys": [["-"]],
      "os": "windows",
      "source": "official",
      "confidence": "high",
      "verified_against_official": true
    },
    {
      "section": "View",
      "action": "Zoom 1:1",
      "keys": [["1"]],
      "os": "windows",
      "source": "official",
      "confidence": "high",
      "verified_against_official": true
    },
    {
      "section": "View",
      "action": "Shrink wrap",
      "keys": [["Ctrl", "E"]],
      "os": "windows",
      "source": "official",
      "confidence": "high",
      "verified_against_official": true
    },
    {
      "section": "View",
      "action": "Fit image in window",
      "keys": [["Ctrl", "Shift", "E"]],
      "os": "windows",
      "source": "official",
      "confidence": "high",
      "verified_against_official": true
    },
    {
      "section": "View",
      "action": "Toggle rulers",
      "keys": [["Ctrl", "Shift", "R"]],
      "os": "windows",
      "source": "official",
      "confidence": "high",
      "verified_against_official": true
    },
    {
      "section": "View",
      "action": "Toggle guides",
      "keys": [["Ctrl", "Shift", "T"]],
      "os": "windows",
      "source": "official",
      "confidence": "high",
      "verified_against_official": true
    },
    {
      "section": "Edit",
      "action": "Undo",
      "keys": [["Ctrl", "Z"]],
      "os": "windows",
      "source": "official",
      "confidence": "high",
      "verified_against_official": true
    },
    {
      "section": "Edit",
      "action": "Redo",
      "keys": [["Ctrl", "Y"]],
      "os": "windows",
      "source": "official",
      "confidence": "high",
      "verified_against_official": true
    },
    {
      "section": "Edit",
      "action": "Copy selection",
      "keys": [["Ctrl", "C"]],
      "os": "windows",
      "source": "official",
      "confidence": "high",
      "verified_against_official": true
    },
    {
      "section": "Edit",
      "action": "Cut selection",
      "keys": [["Ctrl", "X"]],
      "os": "windows",
      "source": "official",
      "confidence": "high",
      "verified_against_official": true
    },
    {
      "section": "Edit",
      "action": "Copy visible",
      "keys": [["Ctrl", "Shift", "C"]],
      "os": "windows",
      "source": "official",
      "confidence": "high",
      "verified_against_official": true
    },
    {
      "section": "Edit",
      "action": "Paste as new image",
      "keys": [["Ctrl", "Shift", "V"]],
      "os": "windows",
      "source": "official",
      "confidence": "high",
      "verified_against_official": true
    },
    {
      "section": "Edit",
      "action": "Paste clipboard",
      "keys": [["Ctrl", "V"]],
      "os": "windows",
      "source": "official",
      "confidence": "high",
      "verified_against_official": true
    },
    {
      "section": "Edit",
      "action": "Clears selection",
      "keys": [["Ctrl", "K"]],
      "os": "windows",
      "source": "official",
      "confidence": "high",
      "verified_against_official": true
    },
    {
      "section": "Edit",
      "action": "Named copy selection",
      "keys": [["Ctrl", "Shift", "C"]],
      "os": "windows",
      "source": "official",
      "confidence": "high",
      "verified_against_official": true
    },
    {
      "section": "Edit",
      "action": "Named cut selection",
      "keys": [["Ctrl", "Shift", "X"]],
      "os": "windows",
      "source": "official",
      "confidence": "high",
      "verified_against_official": true
    },
    {
      "section": "Edit",
      "action": "Named paste clipboard",
      "keys": [["Ctrl", "Shift", "V"]],
      "os": "windows",
      "source": "official",
      "confidence": "high",
      "verified_against_official": true
    },
    {
      "section": "Edit",
      "action": "Fill with foreground color",
      "keys": [["Ctrl", ","]],
      "os": "windows",
      "source": "official",
      "confidence": "high",
      "verified_against_official": true
    },
    {
      "section": "Edit",
      "action": "Fill with background color",
      "keys": [["Ctrl", "."]],
      "os": "windows",
      "source": "official",
      "confidence": "high",
      "verified_against_official": true
    },
    {
      "section": "Edit",
      "action": "Fill with pattern",
      "keys": [["Ctrl", ";"]],
      "os": "windows",
      "source": "official",
      "confidence": "high",
      "verified_against_official": true
    },
    {
      "section": "Layers",
      "action": "Select the layer above",
      "keys": [["PgUp"]],
      "os": "windows",
      "source": "official",
      "confidence": "high",
      "verified_against_official": true
    },
    {
      "section": "Layers",
      "action": "Select the layer below",
      "keys": [["PgDn"]],
      "os": "windows",
      "source": "official",
      "confidence": "high",
      "verified_against_official": true
    },
    {
      "section": "Layers",
      "action": "Select the first layer",
      "keys": [["Home"]],
      "os": "windows",
      "source": "official",
      "confidence": "high",
      "verified_against_official": true
    },
    {
      "section": "Layers",
      "action": "Select the last layer",
      "keys": [["End"]],
      "os": "windows",
      "source": "official",
      "confidence": "high",
      "verified_against_official": true
    },
    {
      "section": "Layers",
      "action": "Merge visible layers",
      "keys": [["Ctrl", "M"]],
      "os": "windows",
      "source": "official",
      "confidence": "high",
      "verified_against_official": true
    },
    {
      "section": "Layers",
      "action": "Anchor layer",
      "keys": [["Ctrl", "H"]],
      "os": "windows",
      "source": "official",
      "confidence": "high",
      "verified_against_official": true
    },
    {
      "section": "Selections",
      "action": "Toggle selections",
      "keys": [["Ctrl", "T"]],
      "os": "windows",
      "source": "official",
      "confidence": "high",
      "verified_against_official": true
    },
    {
      "section": "Selections",
      "action": "Select all",
      "keys": [["Ctrl", "A"]],
      "os": "windows",
      "source": "official",
      "confidence": "high",
      "verified_against_official": true
    },
    {
      "section": "Selections",
      "action": "Select none",
      "keys": [["Ctrl", "Shift", "A"]],
      "os": "windows",
      "source": "official",
      "confidence": "high",
      "verified_against_official": true
    },
    {
      "section": "Selections",
      "action": "Invert selection",
      "keys": [["Ctrl", "I"]],
      "os": "windows",
      "source": "official",
      "confidence": "high",
      "verified_against_official": true
    },
    {
      "section": "Selections",
      "action": "Float selection",
      "keys": [["Ctrl", "Shift", "L"]],
      "os": "windows",
      "source": "official",
      "confidence": "high",
      "verified_against_official": true
    },
    {
      "section": "Selections",
      "action": "Path to selection",
      "keys": [["Shift", "V"]],
      "os": "windows",
      "source": "official",
      "confidence": "high",
      "verified_against_official": true
    },
    {
      "section": "Plug-Ins",
      "action": "Repeat last plug-in",
      "keys": [["Ctrl", "F"]],
      "os": "windows",
      "source": "official",
      "confidence": "high",
      "verified_against_official": true
    },
    {
      "section": "Plug-Ins",
      "action": "Reshow last plug-in",
      "keys": [["Ctrl", "Shift", "F"]],
      "os": "windows",
      "source": "official",
      "confidence": "high",
      "verified_against_official": true
    }
  ]
}
