{
  "app_name": "TablePlus",
  "process_name": "tableplus.exe",
  "category": "Database",
  "platforms": ["windows"],
  "icon_slug": "tableplus",
  "brand_color": "#32A875",
  "shortcuts": [
    { "section": "Global", "action": "Open a New Connection", "keys": [["Ctrl", "N"]], "os": "windows", "source": "official", "confidence": "high", "verified_against_official": true },
    { "section": "Global", "action": "Open Preference", "keys": [["Ctrl", ","]], "os": "windows", "source": "official", "confidence": "high", "verified_against_official": true },
    { "section": "Global", "action": "New SQL Viewer", "keys": [["Ctrl", "Shift", "O"]], "os": "windows", "source": "official", "confidence": "high", "verified_against_official": true },
    { "section": "Workspace", "action": "Close a Tab/Window", "keys": [["Ctrl", "W"]], "os": "windows", "source": "official", "confidence": "high", "verified_against_official": true },
    { "section": "Workspace", "action": "Commit Changes", "keys": [["Ctrl", "S"]], "os": "windows", "source": "official", "confidence": "high", "verified_against_official": true },
    { "section": "Workspace", "action": "Preview Changes", "keys": [["Ctrl", "Shift", "P"]], "os": "windows", "source": "official", "confidence": "high", "verified_against_official": true },
    { "section": "Workspace", "action": "Discard Changes", "keys": [["Ctrl", "Shift", "Delete"]], "os": "windows", "source": "official", "confidence": "high", "verified_against_official": true },
    { "section": "Workspace", "action": "Open a New Tab", "keys": [["Ctrl", "T"]], "os": "windows", "source": "official", "confidence": "high", "verified_against_official": true },
    { "section": "Workspace", "action": "Open Plugin Manager", "keys": [["Ctrl", "L"]], "os": "windows", "source": "official", "confidence": "high", "verified_against_official": true },
    { "section": "Workspace", "action": "Toggle Console Log", "keys": [["Ctrl", "Shift", "C"]], "os": "windows", "source": "official", "confidence": "high", "verified_against_official": true },
    { "section": "Workspace", "action": "Run Custom Script", "keys": [["Ctrl", "."]], "os": "windows", "source": "official", "confidence": "high", "verified_against_official": true },
    { "section": "Workspace", "action": "Reload Workspace", "keys": [["Ctrl", "R"]], "os": "windows", "source": "official", "confidence": "high", "verified_against_official": true },
    { "section": "Workspace", "action": "Navigate to Left Tab", "keys": [["Ctrl", "["]], "os": "windows", "source": "official", "confidence": "high", "verified_against_official": true },
    { "section": "Workspace", "action": "Navigate to Right Tab", "keys": [["Ctrl", "]"]], "os": "windows", "source": "official", "confidence": "high", "verified_against_official": true },
    { "section": "Workspace", "action": "Navigate to Left Pane", "keys": [["Ctrl", "Shift", "["]], "os": "windows", "source": "official", "confidence": "high", "verified_against_official": true },
    { "section": "Workspace", "action": "Navigate to Right Pane", "keys": [["Ctrl", "Shift", "]"]], "os": "windows", "source": "official", "confidence": "high", "verified_against_official": true },
    { "section": "Workspace", "action": "Split Pane Horizontally", "keys": [["Ctrl", "Shift", "D"]], "os": "windows", "source": "official", "confidence": "high", "verified_against_official": true },
    { "section": "Workspace", "action": "Navigate to Number Tab", "keys": [["Ctrl", "1"], ["Ctrl", "2"], ["Ctrl", "3"], ["Ctrl", "4"], ["Ctrl", "5"], ["Ctrl", "6"], ["Ctrl", "7"], ["Ctrl", "8"], ["Ctrl", "9"]], "os": "windows", "source": "official", "confidence": "high", "verified_against_official": true },
    { "section": "Workspace", "action": "Switch Database", "keys": [["Ctrl", "K"]], "os": "windows", "source": "official", "confidence": "high", "verified_against_official": true },
    { "section": "Workspace", "action": "Switch Connection", "keys": [["Ctrl", "Shift", "K"]], "os": "windows", "source": "official", "confidence": "high", "verified_against_official": true },
    { "section": "SQL Tab", "action": "Execute SQL Code", "keys": [["Ctrl", "Enter"]], "os": "windows", "source": "official", "confidence": "high", "verified_against_official": true },
    { "section": "SQL Tab", "action": "Open File SQL", "keys": [["Ctrl", "O"]], "os": "windows", "source": "official", "confidence": "high", "verified_against_official": true },
    { "section": "SQL Tab", "action": "Beautify Selected SQL", "keys": [["Ctrl", "I"]], "os": "windows", "source": "official", "confidence": "high", "verified_against_official": true },
    { "section": "SQL Tab", "action": "Uglify Selected SQL", "keys": [["Ctrl", "Shift", "I"]], "os": "windows", "source": "official", "confidence": "high", "verified_against_official": true },
    { "section": "SQL Tab", "action": "Save Selected SQL As", "keys": [["Ctrl", "Shift", "S"]], "os": "windows", "source": "official", "confidence": "high", "verified_against_official": true },
    { "section": "SQL Tab", "action": "Comment/Uncomment Lines of SQL", "keys": [["Ctrl", "/"]], "os": "windows", "source": "official", "confidence": "high", "verified_against_official": true },
    { "section": "SQL Tab", "action": "Indent Selected SQL Code", "keys": [["Ctrl", "I"]], "os": "windows", "source": "official", "confidence": "high", "verified_against_official": true },
    { "section": "SQL Tab", "action": "Select Next Instance of Current Highlight", "keys": [["Ctrl", "D"]], "os": "windows", "source": "official", "confidence": "high", "verified_against_official": true },
    { "section": "SQL Tab", "action": "Select All Instances of Current Highlight", "keys": [["Ctrl", "Ctrl", "G"]], "os": "windows", "source": "official", "confidence": "high", "verified_against_official": true },
    { "section": "Workspace", "action": "Undo", "keys": [["Ctrl", "Z"]], "os": "windows", "source": "official", "confidence": "high", "verified_against_official": true },
    { "section": "Workspace", "action": "Redo", "keys": [["Ctrl", "Shift", "Z"]], "os": "windows", "source": "official", "confidence": "high", "verified_against_official": true },
    { "section": "Workspace", "action": "Open Anything", "keys": [["Ctrl", "P"]], "os": "windows", "source": "official", "confidence": "high", "verified_against_official": true },
    { "section": "Workspace", "action": "Open SQL Query", "keys": [["Ctrl", "E"]], "os": "windows", "source": "official", "confidence": "high", "verified_against_official": true },
    { "section": "Table Data", "action": "Copy Rows", "keys": [["Ctrl", "C"]], "os": "windows", "source": "official", "confidence": "high", "verified_against_official": true },
    { "section": "Table Data", "action": "Paste Rows", "keys": [["Ctrl", "V"]], "os": "windows", "source": "official", "confidence": "high", "verified_against_official": true },
    { "section": "Table Data", "action": "Duplicate Row", "keys": [["Ctrl", "D"]], "os": "windows", "source": "official", "confidence": "high", "verified_against_official": true },
    { "section": "Table Data", "action": "Insert a New Row", "keys": [["Ctrl", "I"]], "os": "windows", "source": "official", "confidence": "high", "verified_against_official": true },
    { "section": "Table Data", "action": "Open Row Filter", "keys": [["Ctrl", "F"]], "os": "windows", "source": "official", "confidence": "high", "verified_against_official": true },
    { "section": "Table Data", "action": "Open Column Filter", "keys": [["Ctrl", "Alt", "F"]], "os": "windows", "source": "official", "confidence": "high", "verified_against_official": true }
  ]
}
